polka_curses/__init__.py
polka_curses/config.py
polka_curses/controller.py
polka_curses/handler.py
polka_curses/main.py
polka_curses/model.py
polka_curses/view.py
polka_curses/views/__init__.py
polka_curses/views/blogs_page.py
polka_curses/views/book_page.py
polka_curses/views/books_page.py
polka_curses/views/expert_page.py
polka_curses/views/experts_page.py
polka_curses/views/list_page.py
polka_curses/views/lists_page.py
polka_curses/views/loading_page.py
polka_curses/views/podcasts_page.py
polka_curses/views/search_page.py
polka_curses/views/status_bar.py
polka_curses/views/tab_bar.py
polka_curses/views/widgets/__init__.py
polka_curses/views/widgets/scrollable_text.py
polka_curses-1.3.0.dist-info/entry_points.txt
polka_curses-1.3.0.dist-info/LICENSE
polka_curses-1.3.0.dist-info/WHEEL
polka_curses-1.3.0.dist-info/METADATA
polka_curses-1.3.0.dist-info/RECORD
