Metadata-Version: 2.1
Name: polka-curses
Version: 1.3.0
Summary: The curses interface for the Polka website (https://polka.academy/)
Home-page: https://github.com/dmkskn/polka_curses/
License: MIT
Keywords: polka,books,literature,russian,api,urwid,cli,terminal,curses,tui
Author: Dima Koskin
Author-email: dmksknn@gmail.com
Requires-Python: >=3.7,<4.0
Classifier: License :: OSI Approved :: MIT License
Classifier: Programming Language :: Python
Classifier: Programming Language :: Python :: 3
Classifier: Programming Language :: Python :: 3 :: Only
Classifier: Programming Language :: Python :: 3.7
Classifier: Programming Language :: Python :: 3.8
Classifier: Topic :: Software Development :: Libraries
Requires-Dist: polka (>=2.4,<3.0)
Requires-Dist: urwid (>=2.0,<3.0)
